colab_print/__init__.py
colab_print/_core.py
colab_print/exception.py
colab_print/functions.py
colab_print/py.typed
colab_print/utilities.py
colab_print-0.7.1.dist-info/METADATA
colab_print-0.7.1.dist-info/WHEEL
colab_print-0.7.1.dist-info/licenses/LICENSE
colab_print-0.7.1.dist-info/RECORD
