Metadata-Version: 2.4
Name: colab-print
Version: 0.7.1
Summary: Enhanced display utilities for Jupyter/Colab notebooks with customizable styles
Project-URL: Homepage, https://github.com/alaamer12/colab-print
Project-URL: Documentation, https://github.com/alaamer12/colab-print#readme
Project-URL: Issues, https://github.com/alaamer12/colab-print/issues
Author-email: alaamer12 <ahmedmuhmmed239@gmail.com>
Maintainer-email: alaamer12 <ahmedmuhmmed239@gmail.com>
License: MIT
License-File: LICENSE
Keywords: animation,array-visualization,base64,blob,buttons,callbacks,code-display,colab,custom-styles,customization,data-science,dataframe,dataframe-display,dataframe-styles,dictionary-display,display,event-handling,formatting,graceful-fallbacks,html,interactive,ipython,jax,jupyter,markdown,matrix,mermaid,nested-lists,notebook,numpy,output,pandas,pdf,presentation,progress-bar,rich-text,styling,syntax-highlighting,tables,tensorflow,theme-customization,torch,tqdm-compatible,visualization
Classifier: Development Status :: 4 - Beta
Classifier: Framework :: IPython
Classifier: Framework :: Jupyter
Classifier: Intended Audience :: Developers
Classifier: Intended Audience :: Science/Research
Classifier: License :: OSI Approved :: MIT License
Classifier: Programming Language :: Python :: 3
Classifier: Programming Language :: Python :: 3.8
Classifier: Programming Language :: Python :: 3.9
Classifier: Programming Language :: Python :: 3.10
Classifier: Programming Language :: Python :: 3.11
Classifier: Topic :: Scientific/Engineering :: Visualization
Requires-Python: >=3.8
Requires-Dist: html2text>=2024.2.26
Requires-Dist: ipython>=7.0.0
Requires-Dist: markdown>=3.7
Requires-Dist: pandas>=1.0.0
